pysesame2/__init__.py
pysesame2/cli.py
pysesame2/pysesame2.py
pysesame2-1.0.2.dist-info/METADATA
pysesame2-1.0.2.dist-info/WHEEL
pysesame2-1.0.2.dist-info/entry_points.txt
pysesame2-1.0.2.dist-info/top_level.txt
pysesame2-1.0.2.dist-info/RECORD
