Metadata-Version: 2.1
Name: pysesame2
Version: 1.0.2
Summary: Python API for Sesame Smartlock made by CANDY HOUSE, Inc.
Home-page: https://github.com/yagami-cerberus/pysesame2
Author: Candyhouse Inc
Author-email: cerberus@candyhouse.co
License: MIT
Platform: Linux
Platform: Mac OSX
Platform: Windows
Classifier: Environment :: Console
Classifier: Intended Audience :: Developers
Classifier: License :: OSI Approved :: MIT License
Classifier: Operating System :: POSIX
Classifier: Programming Language :: Python :: 3 :: Only
Classifier: Topic :: Software Development :: Libraries :: Python Modules
